foggy/__init__.py
foggy/__main__.py
foggy/exception.py
foggy/filedb.py
foggy/mdns.py
foggy/utils.py
foggy/api/__init__.py
foggy/api/app.py
foggy/api/files.py
foggy/api/hello.py
foggy/api/index.py
foggy_backend-0.1.3.2.dist-info/LICENSE
foggy_backend-0.1.3.2.dist-info/METADATA
foggy_backend-0.1.3.2.dist-info/WHEEL
foggy_backend-0.1.3.2.dist-info/entry_points.txt
foggy_backend-0.1.3.2.dist-info/top_level.txt
foggy_backend-0.1.3.2.dist-info/RECORD
