Metadata-Version: 2.1
Name: foggy-backend
Version: 0.1.3.2
Summary: Foggy backend with REST API for the foggy sync iOS app
Home-page: https://gitlab.com/e9wikner/foggy
Author: Stefan Wikner
Author-email: stefan@stefanwikner.se
License: UNKNOWN
Platform: UNKNOWN
Classifier: Intended Audience :: Developers
Classifier: Intended Audience :: Information Technology
Classifier: Operating System :: POSIX :: Linux
Classifier: Programming Language :: Python :: 3.7
Classifier: Programming Language :: Python :: 3.8
Classifier: Programming Language :: Python :: 3.9
Classifier: License :: OSI Approved :: Apache Software License
License-File: LICENSE
Requires-Dist: falcon
Requires-Dist: gunicorn
Requires-Dist: zeroconf
